basharsquareroot-0.1.0.dist-info/licenses/LICENSE
square_root_lib_bashar/__init__.py
square_root_lib_bashar/__main__.py
square_root_lib_bashar/core.py
basharsquareroot-0.1.0.dist-info/METADATA
basharsquareroot-0.1.0.dist-info/WHEEL
basharsquareroot-0.1.0.dist-info/entry_points.txt
basharsquareroot-0.1.0.dist-info/top_level.txt
basharsquareroot-0.1.0.dist-info/RECORD
