Metadata-Version: 2.4
Name: BasharSquareRoot
Version: 0.1.0
Summary: Calculate the square root of a number
Author: Bashar Mohammed
Author-email: Bashar Mohammed <bsharmshrh00@gmail.com>
License: MIT License
Requires-Python: >=3.7
License-File: LICENSE
Dynamic: author
Dynamic: license-file
Dynamic: requires-python
